whatdido/__init__.py
whatdido/app.py
whatdido/config.py
whatdido/editor.py
whatdido/repo.py
whatdido-0.2.0.dist-info/METADATA
whatdido-0.2.0.dist-info/WHEEL
whatdido-0.2.0.dist-info/entry_points.txt
whatdido-0.2.0.dist-info/RECORD
