Metadata-Version: 2.1
Name: whatdido
Version: 0.2.0
Summary: Use AI to write your git commit messages.
License: GPL-2.0
Author: Evan Nagle
Author-email: evan.nagle@gmail.com
Requires-Python: >=3.11,<=3.13
Classifier: License :: OSI Approved :: GNU General Public License v2 (GPLv2)
Classifier: Programming Language :: Python :: 3
Classifier: Programming Language :: Python :: 3.11
Classifier: Programming Language :: Python :: 3.12
Requires-Dist: gitpython (>=3.1.43,<4.0.0)
Requires-Dist: openai (>=1.14.3,<2.0.0)
Requires-Dist: typer (>=0.12.0,<0.13.0)
